[
  {
    "isim": "Yusuf Eczanesi",
    "adres": "Altıok Mahallesi Aydınlık Caddesi No:32/a Ilçe Tarım Çaprazı Bülent Börek Yanı",
    "telefon": "0 (538) 722-95-91"
  },
  {
    "isim": "Bahar Eczanesi",
    "adres": "İlçe Tarım Karşısı 2 Nolu Sağlık Ocağı Yanı",
    "telefon": "0 (412) 461-21-22"
  },
  {
    "isim": "Zerzevan Eczanesi",
    "adres": "Çınar Devlet Hastanesi Karşısı Sadlık Sokak Cumhuriyet Mahallesi No:5/1",
    "telefon": "0 (412) 511-25-11"
  },
  {
    "isim": "Batı Eczanesi",
    "adres": "Diclekent Ava Düğün Salonu Yanı Batı Hastanesi Karşısı",
    "telefon": "0 (412) 236-40-04"
  },
  {
    "isim": "Zehra Eczanesi",
    "adres": "Fırat Bulvarı Petrol Ofisi Karşısı Çarmar Yanı Gaziler Son Durak",
    "telefon": "0 (412) 251-51-61"
  },
  {
    "isim": "Dicle Eczanesi",
    "adres": "75. Yol Go Petrol'ün Karşısındaki Nazım Hikmet Caddesi Tema Parkı Ve Aslan Market Arası Sol Taraftayız",
    "telefon": "0 (412) 611-80-56"
  },
  {
    "isim": "Serçem Eczanesi",
    "adres": "S. Eyubi Mahallesi, Bayındırlık Ninova Arkası Güneydoğu Taksi Durağı Arkası",
    "telefon": "0 (412) 237-19-88"
  },
  {
    "isim": "Zilan Eczanesi",
    "adres": "5 Nisan Mahallesi, 744. Sokak, Mehmet Cansız Ortaokulu Arkası. Bingöllüler Yas Evi Civarı. Bağlar Sağlık Ocağı Karşısı .",
    "telefon": "0 (412) 235-97-04"
  },
  {
    "isim": "Işık Eczanesi",
    "adres": "Yenihal Caddesi, Toptancılar Sitesi Ilerisi Erbab 3 Sitesi D Blok Altı No:2 Gökkuşağı Düğün Salonu Kavşağı Ali Kuşçu Ortaokulu Karşısı",
    "telefon": "0 (412) 290-35-99"
  },
  {
    "isim": "Yağmur Eczanesi",
    "adres": "Büyük Şehir Belediyesi Karşısı Lise Caddesinde Çamlıca Taksi Durağı Bitişiği , Çarmar Market Karşısı Yenişehir",
    "telefon": "0 (412) 228-04-04"
  },
  {
    "isim": "Şilbe Yolaltı Eczanesi",
    "adres": "Elazığ Caddesi 2. Sanayi Karşısı, Tapu Kadatro Sonrası, Ilk Sağ, Şilbe Caddesi",
    "telefon": "0 (412) 262-12-12"
  },
  {
    "isim": "Akarsu Eczanesi",
    "adres": "Diyarbakır Ili Eğil Ilçesi Yenişehir Mahallesi, Saglık Ocagı Sokak, No:33",
    "telefon": "0 (412) 581-21-23"
  },
  {
    "isim": "Şilan Eczanesi",
    "adres": "Yeni Ergani Devlet Hastanesi Karşısı",
    "telefon": "0 (533) 731-85-96"
  },
  {
    "isim": "Karaz Eczanesi",
    "adres": "Kokulupınar Caddesi, Kocaköy / Diyarbakır",
    "telefon": "0 (412) 224-00-38"
  },
  {
    "isim": "Yeni Lokman Eczanesi",
    "adres": "Turgut Özal Mahallesi, Cengiz Topel Caddesi No:7 Kulp / Diyarbakır",
    "telefon": "0 (412) 831-20-35"
  },
  {
    "isim": "Ferhan Eczanesi",
    "adres": "Karahasan Mahallesi, Diyarbakır Caddesi No:151 Lice / Diyarbakır",
    "telefon": "0 (536) 480-30-96"
  },
  {
    "isim": "Hayat Eczanesi",
    "adres": "Bahçeli Evler Mahallesi Eski Devlet Hastanesi Karşısı",
    "telefon": "0 (412) 711-34-56"
  }
]